lft/__init__.py
lft/__main__.py
lft/app/__init__.py
lft/app/app.py
lft/app/data.py
lft/app/epoch.py
lft/app/logger.py
lft/app/network.py
lft/app/node.py
lft/app/vote.py
lft/app/ui/__init__.py
lft/app/ui/console.py
lft/app/ui/listener.py
lft/consensus/__init__.py
lft/consensus/consensus.py
lft/consensus/election.py
lft/consensus/epoch.py
lft/consensus/events.py
lft/consensus/exceptions.py
lft/consensus/round.py
lft/consensus/messages/__init__.py
lft/consensus/messages/data.py
lft/consensus/messages/message.py
lft/consensus/messages/vote.py
lft/event/__init__.py
lft/event/event.py
lft/event/event_mediator.py
lft/event/event_recorder.py
lft/event/event_register.py
lft/event/event_replayer.py
lft/event/event_simulator.py
lft/event/event_system.py
lft/event/mediators/__init__.py
lft/event/mediators/delayed_event_mediator.py
lft/event/mediators/json_rpc_event_mediator.py
lft/event/mediators/timestamp_event_mediator.py
lft/event/mediators/mixin/__init__.py
lft/event/mediators/mixin/event_mediator_recorder_mixin.py
lft/serialization/__init__.py
lft/serialization/serializable.py
lft/serialization/serializer.py
LFT-0.1.1.dist-info/LICENSE
LFT-0.1.1.dist-info/METADATA
LFT-0.1.1.dist-info/WHEEL
LFT-0.1.1.dist-info/entry_points.txt
LFT-0.1.1.dist-info/top_level.txt
LFT-0.1.1.dist-info/RECORD
