Metadata-Version: 2.1
Name: LFT
Version: 0.1.1
Summary: Loopchain Fault Tolerance
Home-page: https://github.com/icon-project/lft2
Author: ICON Foundation
Author-email: foo@icon.foundation
License: Apache License 2.0
Keywords: lft icon blockchain
Platform: UNKNOWN
Classifier: Intended Audience :: Developers
Classifier: Intended Audience :: System Administrators
Classifier: Natural Language :: English
Classifier: License :: OSI Approved :: Apache Software License
Classifier: Programming Language :: Python
Classifier: Programming Language :: Python :: 3.8
Classifier: Programming Language :: Python :: 3.7
Requires-Python: >=3.7.0
Requires-Dist: jsonrpcclient[aiohttp,requests] (~=3.3.5)
Provides-Extra: app
Requires-Dist: jsonrpcclient[aiohttp,requests] (~=3.3.5) ; extra == 'app'
Requires-Dist: coloredlogs (~=10.0.0) ; extra == 'app'
Requires-Dist: ipython (~=7.9.0) ; extra == 'app'
Provides-Extra: dev
Requires-Dist: jsonrpcclient[aiohttp,requests] (~=3.3.5) ; extra == 'dev'
Requires-Dist: coloredlogs (~=10.0.0) ; extra == 'dev'
Requires-Dist: ipython (~=7.9.0) ; extra == 'dev'
Requires-Dist: mock (~=4.0.1) ; extra == 'dev'
Requires-Dist: pytest (~=4.6.3) ; extra == 'dev'
Requires-Dist: pytest-asyncio (~=0.10.0) ; extra == 'dev'
Provides-Extra: lft
Requires-Dist: jsonrpcclient[aiohttp,requests] (~=3.3.5) ; extra == 'lft'
Provides-Extra: test
Requires-Dist: jsonrpcclient[aiohttp,requests] (~=3.3.5) ; extra == 'test'
Requires-Dist: coloredlogs (~=10.0.0) ; extra == 'test'
Requires-Dist: ipython (~=7.9.0) ; extra == 'test'
Requires-Dist: mock (~=4.0.1) ; extra == 'test'
Requires-Dist: pytest (~=4.6.3) ; extra == 'test'
Requires-Dist: pytest-asyncio (~=0.10.0) ; extra == 'test'
